lab5/designs/semi_cpu/src/seven_segment_display.v
module seven_segment_display(
    input wire clk,
    input wire [31:0] number,
    output reg [6:0] seg,
    output reg [7:0] an
);

    reg [19:0] refresh_counter = 0;
    wire [2:0] refresh_clock;
    
    always @(posedge clk) begin
        refresh_counter <= refresh_counter + 1;
    end
    
    assign refresh_clock = refresh_counter[19:17];
    
    reg [3:0] digit;
    reg [31:0] display_number;
    
    always @(*) begin
        display_number = number;
    end
    
    always @(*) begin
        case (refresh_clock)
            3'b000: begin
                an = 8'b11111110;
                digit = display_number % 10;
            end
            3'b001: begin
                an = 8'b11111101;
                digit = (display_number / 10) % 10;
            end
            3'b010: begin
                an = 8'b11111011;
                digit = (display_number / 100) % 10;
            end
            3'b011: begin
                an = 8'b11110111;
                digit = (display_number / 1000) % 10;
            end
            3'b100: begin
                an = 8'b11101111;
                digit = (display_number / 10000) % 10;
            end
            3'b101: begin
                an = 8'b11011111;
                digit = (display_number / 100000) % 10;
            end
            3'b110: begin
                an = 8'b10111111;
                digit = (display_number / 1000000) % 10;
            end
            3'b111: begin
                an = 8'b01111111;
                digit = (display_number / 10000000) % 10;
            end
        endcase
    end
    
    always @(*) begin
        case (digit)
            4'b0000: seg = 7'b1000000;
            4'b0001: seg = 7'b1111001;
            4'b0010: seg = 7'b0100100;
            4'b0011: seg = 7'b0110000;
            4'b0100: seg = 7'b0011001;
            4'b0101: seg = 7'b0010010;
            4'b0110: seg = 7'b0000010;
            4'b0111: seg = 7'b1111000;
            4'b1000: seg = 7'b0000000;
            4'b1001: seg = 7'b0010000;
            default: seg = 7'b1111111;
        endcase
    end

endmodule

lab5/designs/semi_cpu/src/alu.v
module alu(
    input wire [31:0] A,
    input wire [31:0] B,
    input wire [2:0] alu_op,
    output reg [31:0] result
);

    always @(*) begin
        case (alu_op)
            3'b000, 3'b001: result = 32'b0;           
            3'b010: result = A + B;                   
            3'b011: result = A - B;                   
            3'b100: result = A << B[4:0];            
            3'b101: result = A >> B[4:0];            
            3'b110: result = A + B;                   
            3'b111: result = A - B;                   
            default: result = 32'b0;
        endcase
    end

endmodule

lab5/designs/semi_cpu/src/register_file.v
module register_file(
    input wire CLK,
    input wire WE3,
    input wire [4:0] A1,
    input wire [4:0] A2,
    input wire [4:0] A3,
    input wire [31:0] WD3,
    output reg [31:0] RD1,
    output reg [31:0] RD2
);

  
    reg [31:0] registers [31:0];
    
   
    integer i;
    initial begin
        for (i = 0; i < 32; i = i + 1) begin
            registers[i] = 32'b0;
        end
    end
    
    
    always @(posedge CLK) begin
        if (WE3 && A3 != 5'b0) begin  
            registers[A3] <= WD3;
        end
    end
    
    
    always @(*) begin
        if (A1 == 5'b0)
            RD1 = 32'b0;  
        else
            RD1 = registers[A1];
            
        if (A2 == 5'b0)
            RD2 = 32'b0;  
        else
            RD2 = registers[A2];
    end

endmodule

lab5/designs/semi_cpu/src/instruction_decoder.v
module instruction_decoder(
    input wire [31:0] instruction,
    input wire control,
    output reg [2:0] alu_op,
    output reg [4:0] read_addr1,
    output reg [4:0] read_addr2,
    output reg [4:0] write_addr,
    output reg [31:0] immediate,
    output reg reg_write,
    output reg use_immediate
);

    wire [2:0] opcode = instruction[31:29];
    wire [4:0] rd = instruction[28:24];
    wire [4:0] rs = instruction[23:19];
    wire [4:0] rt = instruction[18:14];
    wire [18:0] imm = instruction[18:0];

    always @(*) begin
        if (!control) begin
            alu_op = 3'b000;
            read_addr1 = 5'b0;
            read_addr2 = 5'b0;
            write_addr = 5'b0;
            immediate = 32'b0;
            reg_write = 1'b0;
            use_immediate = 1'b0;
        end else begin
            read_addr1 = rs;
            read_addr2 = rt;
            write_addr = rd;
            immediate = {{13{imm[18]}}, imm};
            reg_write = 1'b1;
            
            case (opcode)
                3'b000, 3'b001: begin 
                    alu_op = 3'b000;
                    reg_write = 1'b0;
                    use_immediate = 1'b0;
                end
                3'b010: begin 
                    alu_op = 3'b010;
                    use_immediate = 1'b0;
                end
                3'b011: begin 
                    alu_op = 3'b011;
                    use_immediate = 1'b0;
                end
                3'b100: begin 
                    alu_op = 3'b100;
                    use_immediate = 1'b0;
                end
                3'b101: begin 
                    alu_op = 3'b101;
                    use_immediate = 1'b0;
                end
                3'b110: begin 
                    alu_op = 3'b110;
                    use_immediate = 1'b1;
                end
                3'b111: begin 
                    alu_op = 3'b111;
                    use_immediate = 1'b1;
                end
                default: begin
                    alu_op = 3'b000;
                    reg_write = 1'b0;
                    use_immediate = 1'b0;
                end
            endcase
        end
    end

endmodule

lab5/designs/semi_cpu/src/instruction_memory.v
module instruction_memory(
    input wire [4:0] address,
    output reg [31:0] instruction
);

    always @(*) begin
        case (address)
            5'd0: instruction = {3'b110, 5'd10, 5'd0, 19'd10};        
            5'd1: instruction = {3'b110, 5'd15, 5'd0, 19'd15};        
            5'd2: instruction = {3'b010, 5'd25, 5'd10, 5'd15, 14'd0}; 
            5'd3: instruction = {3'b111, 5'd20, 5'd25, 19'd5};        
            5'd4: instruction = {3'b110, 5'd5, 5'd0, 19'd2};          
            5'd5: instruction = {3'b100, 5'd30, 5'd25, 5'd5, 14'd0};  
            default: instruction = 32'h00000000;                       
        endcase
    end

endmodule

lab5/designs/semi_cpu/src/program_counter.v
module program_counter(
    input wire clk,
    input wire reset,
    input wire control,
    output reg [4:0] pc
);

    always @(posedge clk or posedge reset) begin
        if (reset) begin
            pc <= 5'b0;
        end else if (control) begin
            pc <= pc + 1;
        end
        
    end

endmodule

lab5/designs/semi_cpu/src/semi_cpu.v
module semi_cpu(
    input wire clk,
    input wire reset,
    input wire control,
    output reg [31:0] result,
    output wire [6:0] seg,
    output wire [7:0] an
);

    wire [4:0] pc;
    wire [31:0] instruction;
    wire [2:0] alu_op;
    wire [4:0] read_addr1, read_addr2, write_addr;
    wire [31:0] immediate;
    wire reg_write, use_immediate;
    wire [31:0] read_data1, read_data2;
    wire [31:0] alu_input_b;
    wire [31:0] alu_result;
    
    program_counter pc_unit(
        .clk(clk),
        .reset(reset),
        .control(control),
        .pc(pc)
    );
    
    instruction_memory imem(
        .address(pc),
        .instruction(instruction)
    );
    
    instruction_decoder decoder(
        .instruction(instruction),
        .control(control),
        .alu_op(alu_op),
        .read_addr1(read_addr1),
        .read_addr2(read_addr2),
        .write_addr(write_addr),
        .immediate(immediate),
        .reg_write(reg_write),
        .use_immediate(use_immediate)
    );
    
    register_file rf(
        .CLK(clk),
        .WE3(reg_write),
        .A1(read_addr1),
        .A2(read_addr2),
        .A3(write_addr),
        .WD3(alu_result),
        .RD1(read_data1),
        .RD2(read_data2)
    );
    
    assign alu_input_b = use_immediate ? immediate : read_data2;
    
    alu alu_unit(
        .A(read_data1),
        .B(alu_input_b),
        .alu_op(alu_op),
        .result(alu_result)
    );
    
    // Result register - her instruction'da güncellenir
    always @(posedge clk or posedge reset) begin
        if (reset) begin
            result <= 32'b0;
        end else if (reg_write) begin
            result <= alu_result;
        end
    end
    
    seven_segment_display display(
        .clk(clk),
        .number(result),
        .seg(seg),
        .an(an)
    );

endmodule

lab5/designs/semi_cpu/src/testbench_lab5.v
module testbench_lab5;

    reg clk;
    reg reset;
    reg control;
    wire [31:0] result;
    wire [6:0] seg;
    wire [7:0] an;
    
    semi_cpu dut (
        .clk(clk),
        .reset(reset),
        .control(control),
        .result(result),
        .seg(seg),
        .an(an)
    );
    
    initial begin
        clk = 0;
        forever #5 clk = ~clk;
    end
    
    initial begin
        $dumpfile("semi_cpu_tb.vcd");
        $dumpvars(0, testbench_lab5);
        
        reset = 1;
        control = 0;
        
        $display("=== Semi CPU Test Started ===");
        
        #20 reset = 0;
        $display("Time %0t: Reset released, PC = %d", $time, dut.pc);
        
        #10;
        $display("Time %0t: PC = %d, Instruction = %h", $time, dut.pc, dut.instruction);
        $display("         Control = %b, ALU_OP = %b, Reg_Write = %b", control, dut.alu_op, dut.reg_write);
        $display("         Read_Addr1 = %d, Read_Addr2 = %d, Write_Addr = %d", dut.read_addr1, dut.read_addr2, dut.write_addr);
        $display("         Read_Data1 = %d, Read_Data2 = %d, Immediate = %d", dut.read_data1, dut.read_data2, dut.immediate);
        $display("         ALU_A = %d, ALU_B = %d, ALU_Result = %d", dut.alu_unit.A, dut.alu_unit.B, dut.alu_result);
        
        $display("\n=== Instruction 1: ADDI reg10, reg0, 10 ===");
        #10 control = 1;
        #1;
        $display("Time %0t: Control = 1, ALU_OP = %b, Reg_Write = %b", $time, dut.alu_op, dut.reg_write);
        $display("         ALU_A = %d, ALU_B = %d, ALU_Result = %d", dut.alu_unit.A, dut.alu_unit.B, dut.alu_result);
        #9 control = 0;
        #20;
        $display("Time %0t: After ADDI -> PC = %d, Result = %d", $time, dut.pc, result);
        
        $display("\n=== Instruction 2: ADDI reg15, reg0, 15 ===");
        #10 control = 1;
        #1;
        $display("Time %0t: Control = 1, ALU_OP = %b", $time, dut.alu_op);
        $display("         ALU_A = %d, ALU_B = %d, ALU_Result = %d", dut.alu_unit.A, dut.alu_unit.B, dut.alu_result);
        #9 control = 0;
        #20;
        $display("Time %0t: After ADDI -> PC = %d, Result = %d", $time, dut.pc, result);
        
        $display("\n=== Instruction 3: ADD reg25, reg10, reg15 ===");
        #10 control = 1;
        #1;
        $display("Time %0t: Control = 1, ALU_OP = %b", $time, dut.alu_op);
        $display("         ALU_A = %d, ALU_B = %d, ALU_Result = %d", dut.alu_unit.A, dut.alu_unit.B, dut.alu_result);
        #9 control = 0;
        #20;
        $display("Time %0t: After ADD -> PC = %d, Result = %d", $time, dut.pc, result);
        
        $display("\n=== Register File Contents ===");
        $display("Register 10 = %d", dut.rf.registers[10]);
        $display("Register 15 = %d", dut.rf.registers[15]);
        $display("Register 25 = %d", dut.rf.registers[25]);
        
        $display("\n=== Semi CPU Test Completed ===");
        #50 $finish;
    end

endmodule

lab5/designs/semi_cpu/semi_cpu_tb.vcd
$date
	Mon Jun  9 00:50:40 2025
$end
$version
	Icarus Verilog
$end
$timescale
	1s
$end
$scope module testbench_lab5 $end
$var wire 7 ! seg [6:0] $end
$var wire 32 " result [31:0] $end
$var wire 8 # an [7:0] $end
$var reg 1 $ clk $end
$var reg 1 % control $end
$var reg 1 & reset $end
$scope module dut $end
$var wire 1 $ clk $end
$var wire 1 % control $end
$var wire 1 & reset $end
$var wire 5 ' write_addr [4:0] $end
$var wire 1 ( use_immediate $end
$var wire 7 ) seg [6:0] $end
$var wire 1 * reg_write $end
$var wire 32 + read_data2 [31:0] $end
$var wire 32 , read_data1 [31:0] $end
$var wire 5 - read_addr2 [4:0] $end
$var wire 5 . read_addr1 [4:0] $end
$var wire 5 / pc [4:0] $end
$var wire 32 0 instruction [31:0] $end
$var wire 32 1 immediate [31:0] $end
$var wire 8 2 an [7:0] $end
$var wire 32 3 alu_result [31:0] $end
$var wire 3 4 alu_op [2:0] $end
$var wire 32 5 alu_input_b [31:0] $end
$var reg 32 6 result [31:0] $end
$scope module alu_unit $end
$var wire 32 7 B [31:0] $end
$var wire 3 8 alu_op [2:0] $end
$var wire 32 9 A [31:0] $end
$var reg 32 : result [31:0] $end
$upscope $end
$scope module decoder $end
$var wire 1 % control $end
$var wire 5 ; rt [4:0] $end
$var wire 5 < rs [4:0] $end
$var wire 5 = rd [4:0] $end
$var wire 3 > opcode [2:0] $end
$var wire 32 ? instruction [31:0] $end
$var wire 19 @ imm [18:0] $end
$var reg 3 A alu_op [2:0] $end
$var reg 32 B immediate [31:0] $end
$var reg 5 C read_addr1 [4:0] $end
$var reg 5 D read_addr2 [4:0] $end
$var reg 1 * reg_write $end
$var reg 1 ( use_immediate $end
$var reg 5 E write_addr [4:0] $end
$upscope $end
$scope module display $end
$var wire 1 $ clk $end
$var wire 32 F number [31:0] $end
$var wire 3 G refresh_clock [2:0] $end
$var reg 8 H an [7:0] $end
$var reg 4 I digit [3:0] $end
$var reg 32 J display_number [31:0] $end
$var reg 20 K refresh_counter [19:0] $end
$var reg 7 L seg [6:0] $end
$upscope $end
$scope module imem $end
$var wire 5 M address [4:0] $end
$var reg 32 N instruction [31:0] $end
$upscope $end
$scope module pc_unit $end
$var wire 1 $ clk $end
$var wire 1 % control $end
$var wire 1 & reset $end
$var reg 5 O pc [4:0] $end
$upscope $end
$scope module rf $end
$var wire 5 P A1 [4:0] $end
$var wire 5 Q A2 [4:0] $end
$var wire 5 R A3 [4:0] $end
$var wire 1 $ CLK $end
$var wire 32 S WD3 [31:0] $end
$var wire 1 * WE3 $end
$var reg 32 T RD1 [31:0] $end
$var reg 32 U RD2 [31:0] $end
$var integer 32 V i [31:0] $end
$upscope $end
$upscope $end
$upscope $end
$enddefinitions $end
$comment Show the parameter values. $end
$dumpall
$end
#0
$dumpvars
b100000 V
b0 U
b0 T
b0 S
b0 R
b0 Q
b0 P
b0 O
b11001010000000000000000000001010 N
b0 M
b1000000 L
b0 K
b0 J
b0 I
b11111110 H
b0 G
b0 F
b0 E
b0 D
b0 C
b0 B
b0 A
b1010 @
b11001010000000000000000000001010 ?
b110 >
b1010 =
b0 <
b0 ;
b0 :
b0 9
b0 8
b0 7
b0 6
b0 5
b0 4
b0 3
b11111110 2
b0 1
b11001010000000000000000000001010 0
b0 /
b0 .
b0 -
b0 ,
b0 +
0*
b1000000 )
0(
b0 '
1&
0%
0$
b11111110 #
b0 "
b1000000 !
$end
#5
b1 K
1$
#10
0$
#15
b10 K
1$
#20
0$
0&
#25
b11 K
1$
#30
0$
#35
b100 K
1$
#40
b1010 3
b1010 :
b1010 S
b1010 5
b1010 7
1(
b110 4
b110 8
b110 A
1*
b1010 1
b1010 B
b1010 '
b1010 E
b1010 R
0$
1%
#45
b1111 3
b1111 :
b1111 S
b1111 5
b1111 7
b1111 1
b1111 B
b1111 '
b1111 E
b1111 R
b1111 @
b1111 =
b1010 J
b11001111000000000000000000001111 0
b11001111000000000000000000001111 ?
b11001111000000000000000000001111 N
b101 K
b1010 "
b1010 6
b1010 F
b1 /
b1 M
b1 O
1$
#50
b0 5
b0 7
b0 3
b0 :
b0 S
0(
0*
b0 1
b0 B
b0 '
b0 E
b0 R
b0 4
b0 8
b0 A
0$
0%
#55
b110 K
1$
#60
0$
#65
b111 K
1$
#70
0$
#75
b1000 K
1$
#80
b1111 3
b1111 :
b1111 S
b1111 5
b1111 7
1(
b110 4
b110 8
b110 A
1*
b1111 1
b1111 B
b1111 '
b1111 E
b1111 R
0$
1%
#85
b11001 3
b11001 :
b11001 S
b1111 +
b1111 U
b1010 ,
b1010 9
b1010 T
b10010 !
b10010 )
b10010 L
0(
b10 4
b10 8
b10 A
b111100000000000000 1
b111100000000000000 B
b11001 '
b11001 E
b11001 R
b1111 -
b1111 D
b1111 Q
b1010 .
b1010 C
b1010 P
b101 I
b111100000000000000 @
b1111 ;
b1010 <
b11001 =
b10 >
b1111 J
b1011001010100111100000000000000 0
b1011001010100111100000000000000 ?
b1011001010100111100000000000000 N
b1001 K
b1111 "
b1111 6
b1111 F
b10 /
b10 M
b10 O
1$
#90
b0 5
b0 7
b0 +
b0 U
b0 ,
b0 9
b0 T
b0 3
b0 :
b0 S
0*
b0 1
b0 B
b0 '
b0 E
b0 R
b0 -
b0 D
b0 Q
b0 .
b0 C
b0 P
b0 4
b0 8
b0 A
0$
0%
#95
b1010 K
1$
#100
0$
#105
b1011 K
1$
#110
0$
#115
b1100 K
1$
#120
b1111 5
b1111 7
b11001 3
b11001 :
b11001 S
b1111 +
b1111 U
b1010 ,
b1010 9
b1010 T
b10 4
b10 8
b10 A
1*
b111100000000000000 1
b111100000000000000 B
b11001 '
b11001 E
b11001 R
b1111 -
b1111 D
b1111 Q
b1010 .
b1010 C
b1010 P
0$
1%
#125
b101 5
b101 7
b10100 3
b10100 :
b10100 S
b0 +
b0 U
b11001 ,
b11001 9
b11001 T
1(
b111 4
b111 8
b111 A
b101 1
b101 B
b10100 '
b10100 E
b10100 R
b0 -
b0 D
b0 Q
b11001 .
b11001 C
b11001 P
b101 @
b0 ;
b11001 <
b10100 =
b111 >
b11001 J
b11110100110010000000000000000101 0
b11110100110010000000000000000101 ?
b11110100110010000000000000000101 N
b1101 K
b11001 "
b11001 6
b11001 F
b11 /
b11 M
b11 O
1$
#130
b0 5
b0 7
b0 ,
b0 9
b0 T
b0 3
b0 :
b0 S
0(
0*
b0 1
b0 B
b0 '
b0 E
b0 R
b0 .
b0 C
b0 P
b0 4
b0 8
b0 A
0$
0%
#135
b1110 K
1$
#140
0$
#145
b1111 K
1$
#150
0$
#155
b10000 K
1$
#160
0$
#165
b10001 K
1$
#170
0$
#175
b10010 K
1$
#180
0$
#185
b10011 K
1$
#190
0$
#195
b10100 K
1$
