lab4/designs/cpu_core/src/alu.v
module alu(
    input wire [31:0] A,
    input wire [31:0] B,
    input wire [1:0] opcode,
    output reg [31:0] result
);

    always @(*) begin
        case (opcode)
            2'b00: result = A + B;           
            2'b01: result = A - B;          
            2'b10: result = A << B[4:0];     
            2'b11: result = A >> B[4:0];     
            default: result = 32'b0;
        endcase
    end

endmodule

lab4/designs/cpu_core/src/register_file.v
module register_file(
    input wire CLK,
    input wire WE3,
    input wire [4:0] A1,
    input wire [4:0] A2,
    input wire [4:0] A3,
    input wire [31:0] WD3,
    output reg [31:0] RD1,
    output reg [31:0] RD2
);

  
    reg [31:0] registers [31:0];
    
    
    integer i;
    initial begin
        for (i = 0; i < 32; i = i + 1) begin
            registers[i] = 32'b0;
        end
    end
    
    
    always @(posedge CLK) begin
        if (WE3 && A3 != 5'b0) begin  
            registers[A3] <= WD3;
        end
    end
    
   
    always @(*) begin
        if (A1 == 5'b0)
            RD1 = 32'b0; 
        else
            RD1 = registers[A1];
            
        if (A2 == 5'b0)
            RD2 = 32'b0; 
        else
            RD2 = registers[A2];
    end

endmodule

lab4/designs/cpu_core/src/cpu_core.v
module cpu_core(
    input wire CLK,
    input wire reset,
    input wire [4:0] read_addr1,
    input wire [4:0] read_addr2,
    input wire [4:0] write_addr,
    input wire [31:0] write_data,
    input wire write_enable,
    input wire [1:0] alu_op,
    output wire [31:0] alu_result,
    output wire [31:0] read_data1,
    output wire [31:0] read_data2
);

    wire [31:0] reg_data1, reg_data2;
    
   
    register_file rf(
        .CLK(CLK),
        .WE3(write_enable),
        .A1(read_addr1),
        .A2(read_addr2),
        .A3(write_addr),
        .WD3(write_data),
        .RD1(reg_data1),
        .RD2(reg_data2)
    );
    
    
    alu alu_unit(
        .A(reg_data1),
        .B(reg_data2),
        .opcode(alu_op),
        .result(alu_result)
    );
    
   
    assign read_data1 = reg_data1;
    assign read_data2 = reg_data2;

endmodule

lab4/designs/cpu_core/src/testbench.v
module testbench;

    
    reg CLK;
    reg reset;
    reg [4:0] read_addr1, read_addr2, write_addr;
    reg [31:0] write_data;
    reg write_enable;
    reg [1:0] alu_op;
    wire [31:0] alu_result;
    wire [31:0] read_data1, read_data2;
    
    
    cpu_core dut (
        .CLK(CLK),
        .reset(reset),
        .read_addr1(read_addr1),
        .read_addr2(read_addr2),
        .write_addr(write_addr),
        .write_data(write_data),
        .write_enable(write_enable),
        .alu_op(alu_op),
        .alu_result(alu_result),
        .read_data1(read_data1),
        .read_data2(read_data2)
    );
    
   
    initial begin
        CLK = 0;
        forever #5 CLK = ~CLK;  
    end
    
    
    initial begin
        $dumpfile("cpu_core_tb.vcd");
        $dumpvars(0, testbench);
        
       
        reset = 1;
        write_enable = 0;
        read_addr1 = 0;
        read_addr2 = 0;
        write_addr = 0;
        write_data = 0;
        alu_op = 0;
        
        #10 reset = 0;
        
        
        $display("=== Test 1: ADD Operation ===");
        
        
        #10 write_addr = 5'd10;
        write_data = 32'd10;
        write_enable = 1;
        #10 write_enable = 0;
        
        
        #10 write_addr = 5'd15;
        write_data = 32'd15;
        write_enable = 1;
        #10 write_enable = 0;
        
        
        #10 read_addr1 = 5'd10;
        read_addr2 = 5'd15;
        alu_op = 2'b00; 
        #10;
        $display("ADD: %d + %d = %d", read_data1, read_data2, alu_result);
        
        
        write_addr = 5'd20;
        write_data = alu_result;
        write_enable = 1;
        #10 write_enable = 0;
        
        
        $display("=== Test 2: SUB Operation ===");
        
       
        #10 write_addr = 5'd10;
        write_data = 32'd20;
        write_enable = 1;
        #10 write_enable = 0;
        
        
        #10 write_addr = 5'd15;
        write_data = 32'd15;
        write_enable = 1;
        #10 write_enable = 0;
        
        
        #10 read_addr1 = 5'd10;
        read_addr2 = 5'd15;
        alu_op = 2'b01;  
        #10;
        $display("SUB: %d - %d = %d", read_data1, read_data2, alu_result);
        
        
        write_addr = 5'd20;
        write_data = alu_result;
        write_enable = 1;
        #10 write_enable = 0;
        
       
        $display("=== Test 3: SHIFTL Operation ===");
        
       
        #10 write_addr = 5'd10;
        write_data = 32'd31;
        write_enable = 1;
        #10 write_enable = 0;
        
       
        #10 write_addr = 5'd15;
        write_data = 32'd2;
        write_enable = 1;
        #10 write_enable = 0;
        
        
        #10 read_addr1 = 5'd10;
        read_addr2 = 5'd15;
        alu_op = 2'b10;  
        #10;
        $display("SHIFTL: %d << %d = %d", read_data1, read_data2, alu_result);
        
       
        write_addr = 5'd20;
        write_data = alu_result;
        write_enable = 1;
        #10 write_enable = 0;
        
        
        $display("=== Test 4: SHIFTR Operation ===");
        
        
        #10 read_addr1 = 5'd10;
        read_addr2 = 5'd15;
        alu_op = 2'b11; 
        #10;
        $display("SHIFTR: %d >> %d = %d", read_data1, read_data2, alu_result);
        
        
        write_addr = 5'd20;
        write_data = alu_result;
        write_enable = 1;
        #10 write_enable = 0;
        
        
        #10 read_addr1 = 5'd20;
        #10;
        $display("Final value in register 20: %d", read_data1);
        
        $display("=== All tests completed ===");
        #50 $finish;
    end

endmodule

lab4/designs/cpu_core/cpu_core_tb.vcd
$date
	Mon Jun  9 00:49:58 2025
$end
$version
	Icarus Verilog
$end
$timescale
	1s
$end
$scope module testbench $end
$var wire 32 ! read_data2 [31:0] $end
$var wire 32 " read_data1 [31:0] $end
$var wire 32 # alu_result [31:0] $end
$var reg 1 $ CLK $end
$var reg 2 % alu_op [1:0] $end
$var reg 5 & read_addr1 [4:0] $end
$var reg 5 ' read_addr2 [4:0] $end
$var reg 1 ( reset $end
$var reg 5 ) write_addr [4:0] $end
$var reg 32 * write_data [31:0] $end
$var reg 1 + write_enable $end
$scope module dut $end
$var wire 1 $ CLK $end
$var wire 2 , alu_op [1:0] $end
$var wire 5 - read_addr1 [4:0] $end
$var wire 5 . read_addr2 [4:0] $end
$var wire 32 / read_data1 [31:0] $end
$var wire 32 0 read_data2 [31:0] $end
$var wire 1 ( reset $end
$var wire 5 1 write_addr [4:0] $end
$var wire 32 2 write_data [31:0] $end
$var wire 1 + write_enable $end
$var wire 32 3 reg_data2 [31:0] $end
$var wire 32 4 reg_data1 [31:0] $end
$var wire 32 5 alu_result [31:0] $end
$scope module alu_unit $end
$var wire 2 6 opcode [1:0] $end
$var wire 32 7 B [31:0] $end
$var wire 32 8 A [31:0] $end
$var reg 32 9 result [31:0] $end
$upscope $end
$scope module rf $end
$var wire 5 : A1 [4:0] $end
$var wire 5 ; A2 [4:0] $end
$var wire 5 < A3 [4:0] $end
$var wire 1 $ CLK $end
$var wire 32 = WD3 [31:0] $end
$var wire 1 + WE3 $end
$var reg 32 > RD1 [31:0] $end
$var reg 32 ? RD2 [31:0] $end
$var integer 32 @ i [31:0] $end
$upscope $end
$upscope $end
$upscope $end
$enddefinitions $end
$comment Show the parameter values. $end
$dumpall
$end
#0
$dumpvars
b100000 @
b0 ?
b0 >
b0 =
b0 <
b0 ;
b0 :
b0 9
b0 8
b0 7
b0 6
b0 5
b0 4
b0 3
b0 2
b0 1
b0 0
b0 /
b0 .
b0 -
b0 ,
0+
b0 *
b0 )
1(
b0 '
b0 &
b0 %
0$
b0 #
b0 "
b0 !
$end
#5
1$
#10
0$
0(
#15
1$
#20
0$
1+
b1010 *
b1010 2
b1010 =
b1010 )
b1010 1
b1010 <
#25
1$
#30
0$
0+
#35
1$
#40
0$
1+
b1111 *
b1111 2
b1111 =
b1111 )
b1111 1
b1111 <
#45
1$
#50
0$
0+
#55
1$
#60
b11001 #
b11001 5
b11001 9
b1111 !
b1111 0
b1111 3
b1111 7
b1111 ?
b1010 "
b1010 /
b1010 4
b1010 8
b1010 >
0$
b1111 '
b1111 .
b1111 ;
b1010 &
b1010 -
b1010 :
#65
1$
#70
0$
1+
b11001 *
b11001 2
b11001 =
b10100 )
b10100 1
b10100 <
#75
1$
#80
0$
0+
#85
1$
#90
0$
1+
b10100 *
b10100 2
b10100 =
b1010 )
b1010 1
b1010 <
#95
b100011 #
b100011 5
b100011 9
b10100 "
b10100 /
b10100 4
b10100 8
b10100 >
1$
#100
0$
0+
#105
1$
#110
0$
1+
b1111 *
b1111 2
b1111 =
b1111 )
b1111 1
b1111 <
#115
1$
#120
0$
0+
#125
1$
#130
b101 #
b101 5
b101 9
0$
b1 %
b1 ,
b1 6
#135
1$
#140
0$
1+
b101 *
b101 2
b101 =
b10100 )
b10100 1
b10100 <
#145
1$
#150
0$
0+
#155
1$
#160
0$
1+
b11111 *
b11111 2
b11111 =
b1010 )
b1010 1
b1010 <
#165
b10000 #
b10000 5
b10000 9
b11111 "
b11111 /
b11111 4
b11111 8
b11111 >
1$
#170
0$
0+
#175
1$
#180
0$
1+
b10 *
b10 2
b10 =
b1111 )
b1111 1
b1111 <
#185
b11101 #
b11101 5
b11101 9
b10 !
b10 0
b10 3
b10 7
b10 ?
1$
#190
0$
0+
#195
1$
#200
b1111100 #
b1111100 5
b1111100 9
0$
b10 %
b10 ,
b10 6
#205
1$
#210
0$
1+
b1111100 *
b1111100 2
b1111100 =
b10100 )
b10100 1
b10100 <
#215
1$
#220
0$
0+
#225
1$
#230
b111 #
b111 5
b111 9
0$
b11 %
b11 ,
b11 6
#235
1$
#240
0$
1+
b111 *
b111 2
b111 =
#245
1$
#250
0$
0+
#255
1$
#260
b1 #
b1 5
b1 9
b111 "
b111 /
b111 4
b111 8
b111 >
0$
b10100 &
b10100 -
b10100 :
